MANIFEST.in
README.rst
setup.cfg
setup.py
kqueen/__init__.py
kqueen/__main__.py
kqueen/conftest.py
kqueen/exceptions.py
kqueen/gunicorn.py
kqueen/helpers.py
kqueen/kubeapi.py
kqueen/middleware.py
kqueen/models.py
kqueen/serializers.py
kqueen/server.py
kqueen/wsgi.py
kqueen.egg-info/PKG-INFO
kqueen.egg-info/SOURCES.txt
kqueen.egg-info/dependency_links.txt
kqueen.egg-info/entry_points.txt
kqueen.egg-info/not-zip-safe
kqueen.egg-info/requires.txt
kqueen.egg-info/top_level.txt
kqueen/auth/__init__.py
kqueen/auth/base.py
kqueen/auth/common.py
kqueen/auth/ldap.py
kqueen/auth/local.py
kqueen/auth/test_base.py
kqueen/auth/test_common.py
kqueen/auth/test_ldap.py
kqueen/blueprints/__init__.py
kqueen/blueprints/api/__init__.py
kqueen/blueprints/api/generic_views.py
kqueen/blueprints/api/helpers.py
kqueen/blueprints/api/test_cluster.py
kqueen/blueprints/api/test_crud.py
kqueen/blueprints/api/test_helpers.py
kqueen/blueprints/api/test_organization.py
kqueen/blueprints/api/test_provisioner.py
kqueen/blueprints/api/test_user.py
kqueen/blueprints/api/tests.py
kqueen/blueprints/api/views.py
kqueen/blueprints/metrics/__init__.py
kqueen/blueprints/metrics/helpers.py
kqueen/blueprints/metrics/test_helpers.py
kqueen/blueprints/metrics/test_views.py
kqueen/blueprints/metrics/views.py
kqueen/config/__init__.py
kqueen/config/base.py
kqueen/config/default_policy.json
kqueen/config/demo.py
kqueen/config/dev.py
kqueen/config/prod.py
kqueen/config/test.py
kqueen/config/tests.py
kqueen/config/utils.py
kqueen/engines/__init__.py
kqueen/engines/aks.py
kqueen/engines/base.py
kqueen/engines/gce.py
kqueen/engines/jenkins.py
kqueen/engines/manual.py
kqueen/engines/openstack_kubespray.py
kqueen/engines/test_aks.py
kqueen/engines/test_base.py
kqueen/engines/test_gce.py
kqueen/engines/test_jenkins.py
kqueen/engines/test_manual.py
kqueen/storages/__init__.py
kqueen/storages/etcd.py
kqueen/storages/exceptions.py
kqueen/storages/test_client.py
kqueen/storages/test_model_fields.py
kqueen/tests/__init__.py
kqueen/tests/run_aks_test.py
kqueen/tests/run_gke_test.py
kqueen/tests/test_auth.py
kqueen/tests/test_helpers.py
kqueen/tests/test_kubeapi.py
kqueen/tests/test_manual_cluster.py
kqueen/tests/test_models.py
