Metadata-Version: 2.1
Name: kqueen
Version: 1.0
Summary: Kubernetes cluster orchestrator
Home-page: https://github.com/Mirantis/kqueen/
Author: Tomáš Kukrál
Author-email: tomas.kukral@6shore.net
License: MIT
Download-URL: https://github.com/Mirantis/kqueen/archive/v1.0.tar.gz
Platform: UNKNOWN
Classifier: Operating System :: POSIX :: Linux
Classifier: Programming Language :: Python
Classifier: Programming Language :: Python :: Implementation :: CPython
Classifier: Programming Language :: Python :: 3
Classifier: Programming Language :: Python :: 3.6
Provides-Extra: dev
Provides-Extra: test
